lfx/__init__.py
lfx/__main__.py
lfx/constants.py
lfx/py.typed
lfx/settings.py
lfx/type_extraction.py
lfx/_assets/component_index.json
lfx/_assets/nightly_hash_history.json
lfx/_assets/stable_hash_history.json
lfx/base/__init__.py
lfx/base/constants.py
lfx/base/agents/__init__.py
lfx/base/agents/agent.py
lfx/base/agents/altk_base_agent.py
lfx/base/agents/altk_tool_wrappers.py
lfx/base/agents/callback.py
lfx/base/agents/context.py
lfx/base/agents/default_prompts.py
lfx/base/agents/errors.py
lfx/base/agents/events.py
lfx/base/agents/utils.py
lfx/base/agents/crewai/__init__.py
lfx/base/agents/crewai/crew.py
lfx/base/agents/crewai/tasks.py
lfx/base/astra_assistants/__init__.py
lfx/base/astra_assistants/util.py
lfx/base/chains/__init__.py
lfx/base/chains/model.py
lfx/base/composio/__init__.py
lfx/base/composio/composio_base.py
lfx/base/compressors/__init__.py
lfx/base/compressors/model.py
lfx/base/curl/__init__.py
lfx/base/curl/parse.py
lfx/base/data/__init__.py
lfx/base/data/base_file.py
lfx/base/data/cloud_storage_utils.py
lfx/base/data/docling_utils.py
lfx/base/data/storage_utils.py
lfx/base/data/utils.py
lfx/base/datastax/__init__.py
lfx/base/datastax/astradb_base.py
lfx/base/document_transformers/__init__.py
lfx/base/document_transformers/model.py
lfx/base/embeddings/__init__.py
lfx/base/embeddings/aiml_embeddings.py
lfx/base/embeddings/embeddings_class.py
lfx/base/embeddings/model.py
lfx/base/flow_processing/__init__.py
lfx/base/flow_processing/utils.py
lfx/base/huggingface/__init__.py
lfx/base/huggingface/model_bridge.py
lfx/base/io/__init__.py
lfx/base/io/chat.py
lfx/base/io/text.py
lfx/base/knowledge_bases/__init__.py
lfx/base/knowledge_bases/knowledge_base_utils.py
lfx/base/langchain_utilities/__init__.py
lfx/base/langchain_utilities/model.py
lfx/base/langchain_utilities/spider_constants.py
lfx/base/langwatch/__init__.py
lfx/base/langwatch/utils.py
lfx/base/mcp/__init__.py
lfx/base/mcp/constants.py
lfx/base/mcp/util.py
lfx/base/memory/__init__.py
lfx_nightly-0.3.0.dev35.dist-info/METADATA
lfx_nightly-0.3.0.dev35.dist-info/WHEEL
lfx_nightly-0.3.0.dev35.dist-info/entry_points.txt
lfx_nightly-0.3.0.dev35.dist-info/RECORD
